hsh/__init__.py
hsh/app.py
hsh/settings.py
hsh/library/__init__.py
hsh/library/hash.py
hsh-1.1.0.dist-info/DESCRIPTION.rst
hsh-1.1.0.dist-info/METADATA
hsh-1.1.0.dist-info/RECORD
hsh-1.1.0.dist-info/WHEEL
hsh-1.1.0.dist-info/entry_points.txt
hsh-1.1.0.dist-info/metadata.json
hsh-1.1.0.dist-info/top_level.txt
