Metadata-Version: 1.1
Name: hsh
Version: 1.1.0
Summary: Simple file hash digests and file integrity checks
Home-page: https://github.com/chrissimpkins/hsh
Author: Christopher Simpkins
Author-email: UNKNOWN
License: MIT license
Keywords: file,hash,hash digest,checksum,file comparison,file integrity,file checksum,file check,SHA,MD5,SHA1,SHA224,SHA256,SHA384,SHA512
Platform: any
Classifier: Intended Audience :: End Users/Desktop
Classifier: Development Status :: 5 - Production/Stable
Classifier: Natural Language :: English
Classifier: License :: OSI Approved :: MIT License
Classifier: Programming Language :: Python
Classifier: Programming Language :: Python :: 2
Classifier: Programming Language :: Python :: 3
Classifier: Operating System :: MacOS :: MacOS X
Classifier: Operating System :: POSIX
Classifier: Operating System :: Unix
Classifier: Operating System :: Microsoft :: Windows
